endevre_id_client/__init__.py
endevre_id_client/client.py
endevre_id_client/constants.py
endevre_id_client/exceptions.py
endevre_id_client/jwt_utils.py
endevre_id_client/py.typed
endevre_id_client-0.1.0.dist-info/METADATA
endevre_id_client-0.1.0.dist-info/WHEEL
endevre_id_client-0.1.0.dist-info/top_level.txt
endevre_id_client-0.1.0.dist-info/RECORD
