Metadata-Version: 2.4
Name: endevre-id-client
Version: 0.1.0
Summary: Python client for Endevre ID authentication flows
Author-email: Endevre <dev@endevre.com>
License: MIT
Project-URL: Homepage, https://github.com/endevre/id-client-auth
Project-URL: Repository, https://github.com/endevre/id-client-auth
Keywords: endevre,authentication,sso,oauth,jwt
Classifier: Programming Language :: Python
Classifier: Programming Language :: Python :: 3
Classifier: Programming Language :: Python :: 3.9
Classifier: Programming Language :: Python :: 3.10
Classifier: Programming Language :: Python :: 3.11
Classifier: Programming Language :: Python :: 3.12
Classifier: License :: OSI Approved :: MIT License
Classifier: Operating System :: OS Independent
Requires-Python: >=3.9
Requires-Dist: requests<3,>=2.31
Requires-Dist: pyjwt[crypto]<3,>=2.8
Provides-Extra: dev
Requires-Dist: pytest<9,>=8; extra == "dev"
Requires-Dist: pytest-httpserver>=1.0.8; extra == "dev"
